pully/__init__.py
pully/__main__.py
pully/_version.py
pully/constants.py
pully/main.py
pully/models.py
pully/pullyfile.py
pully/cli/__init__.py
pully/cli/_options.py
pully/cli/add_command.py
pully/cli/get_command.py
pully/cli/init_command.py
pully/cli/ls_command.py
pully/cli/run_command.py
pully-0.11.2.dist-info/licenses/LICENSE
pully-0.11.2.dist-info/licenses/NOTICE
pully-0.11.2.dist-info/METADATA
pully-0.11.2.dist-info/WHEEL
pully-0.11.2.dist-info/entry_points.txt
pully-0.11.2.dist-info/top_level.txt
pully-0.11.2.dist-info/RECORD
