Metadata-Version: 2.4
Name: pully
Version: 0.11.2
Summary: Get all the projects with pully! 🪀
Author-email: Digital Safety Research Institute <contact@dsri.org>
License: Apache-2.0
Project-URL: Home, https://gitlab.com/saferatday0/pully
Project-URL: Issues, https://gitlab.com/saferatday0/pully/-/issues
Classifier: Development Status :: 2 - Pre-Alpha
Classifier: Intended Audience :: Developers
Classifier: Programming Language :: Python :: 3
Classifier: Programming Language :: Python :: 3.9
Classifier: Programming Language :: Python :: 3.10
Classifier: Programming Language :: Python :: 3.11
Classifier: Programming Language :: Python :: 3.12
Classifier: Programming Language :: Python :: 3.13
Requires-Python: >=3.9
License-File: LICENSE
License-File: NOTICE
Requires-Dist: msgspec
Requires-Dist: python-gitlab
Requires-Dist: tabulate
Requires-Dist: termcolor
Dynamic: license-file
